{
   "fields" : [
      {
         "display_name" : "Platform",
         "id" : 5,
         "is_custom" : false,
         "is_mandatory" : false,
         "is_on_bug_entry" : false,
         "name" : "rep_platform",
         "type" : 2,
         "value_field" : null,
         "values" : [
            {
               "name" : "Unlisted Binaries",
               "sort_key" : 100,
               "sortkey" : 100,
               "visibility_values" : []
            },
            {
               "name" : "Compiled Sources",
               "sort_key" : 200,
               "sortkey" : 200,
               "visibility_values" : []
            },
            {
               "name" : "MS Windows",
               "sort_key" : 930,
               "sortkey" : 930,
               "visibility_values" : []
            },
            {
               "name" : "unspecified",
               "sort_key" : 2300,
               "sortkey" : 2300,
               "visibility_values" : []
            },
            {
               "name" : "Other",
               "sort_key" : 2350,
               "sortkey" : 2350,
               "visibility_values" : []
            }
         ],
         "visibility_field" : null,
         "visibility_values" : []
      }
   ]
}

